piano_analytics_api/__init__.py
piano_analytics_api/_version.py
piano_analytics_api/api.py
piano_analytics_api/exceptions.py
piano_analytics_api/period.py
piano_analytics_api/pfilter.py
piano_analytics_api/py.typed
piano_analytics_api-1.0.0.dist-info/METADATA
piano_analytics_api-1.0.0.dist-info/WHEEL
piano_analytics_api-1.0.0.dist-info/licenses/LICENSE
piano_analytics_api-1.0.0.dist-info/RECORD
