Metadata-Version: 2.3
Name: piano_analytics_api
Version: 1.0.0
Summary: Python implementation for the Piano Anaytics Reporting API (formerly ‘At Internet’)
Project-URL: Homepage, https://github.com/omroepgelderland/piano-analytics-python-api
Project-URL: Issues, https://github.com/omroepgelderland/piano-analytics-python-api/issues
Project-URL: source_archive, https://github.com/omroepgelderland/piano-analytics-python-api/archive/cabfc3b935dabdd2e150cb7444bae54600368907.zip
Author-email: Remy Glaser <rglaser@gld.nl>
Keywords: at internet,piano analytics
Classifier: License :: OSI Approved :: MIT License
Classifier: Operating System :: OS Independent
Classifier: Programming Language :: Python :: 3
Requires-Python: >=3.9
